__init__.py
coinstac_computation_debugger/__init__.py
coinstac_computation_debugger/computation_debugger.py
coinstac_computation_debugger/debugger_usage_example.py
coinstac_computation_debugger-0.0.1.dist-info/LICENSE
coinstac_computation_debugger-0.0.1.dist-info/METADATA
coinstac_computation_debugger-0.0.1.dist-info/WHEEL
coinstac_computation_debugger-0.0.1.dist-info/top_level.txt
coinstac_computation_debugger-0.0.1.dist-info/RECORD
