Metadata-Version: 2.1
Name: coinstac_computation_debugger
Version: 0.0.1
Summary: This software help in real time debugging coinstac computation code without any modification.
Author: Sunitha Basodi
Project-URL: Homepage, https://github.com/trendscenter/coinstac_computation_debugger
Project-URL: Issues, https://github.com/trendscenter/coinstac_computation_debugger/issues
Classifier: Programming Language :: Python :: 3
Classifier: License :: OSI Approved :: MIT License
Classifier: Operating System :: OS Independent
Requires-Python: >=3.8
License-File: LICENSE
